byaldi/RAGModel.py
byaldi/__init__.py
byaldi/colpali.py
byaldi/objects.py
byaldi/integrations/__init__.py
byaldi/integrations/_langchain.py
Byaldi-0.0.7.dist-info/LICENSE
Byaldi-0.0.7.dist-info/METADATA
Byaldi-0.0.7.dist-info/WHEEL
Byaldi-0.0.7.dist-info/top_level.txt
Byaldi-0.0.7.dist-info/RECORD
