Metadata-Version: 2.1
Name: Byaldi
Version: 0.0.7
Summary: Use late-interaction multi-modal models such as ColPali in just a few lines of code.
Author-email: Ben Clavié <bc@answer.ai>
Maintainer-email: Ben Clavié <bc@answer.ai>, Tony Wu <tony.wu@illuin.tech>
License: Apache License
Project-URL: Homepage, https://github.com/answerdotai/byaldi
Keywords: reranking,retrieval,rag,nlp,colpali,colbert,multi-modal
Requires-Python: >=3.9
License-File: LICENSE
Requires-Dist: colpali-engine <0.4.0,>=0.3.4
Requires-Dist: ml-dtypes
Requires-Dist: mteb ==1.6.35
Requires-Dist: ninja
Requires-Dist: pdf2image
Requires-Dist: srsly
Requires-Dist: torch
Requires-Dist: transformers >=4.42.0
Provides-Extra: dev
Requires-Dist: pytest >=7.4.0 ; extra == 'dev'
Requires-Dist: ruff >=0.1.9 ; extra == 'dev'
Provides-Extra: langchain
Requires-Dist: langchain-core ; extra == 'langchain'
Provides-Extra: server
Requires-Dist: uvicorn ; extra == 'server'
Requires-Dist: fastapi ; extra == 'server'
